common_captcha/__init__.py
common_captcha/config.py
common_captcha/resource/__init__.py
common_captcha/resource/captcha/images/1.jpg
common_captcha/resource/captcha/images/2.jpg
common_captcha/resource/captcha/images/3.jpg
common_captcha/resource/captcha/images/4.jpg
common_captcha/resource/captcha/images/5.jpg
common_captcha/resource/defaultImages/jigsaw/original/1.png
common_captcha/resource/defaultImages/jigsaw/original/2.png
common_captcha/resource/defaultImages/jigsaw/original/3.png
common_captcha/resource/defaultImages/jigsaw/original/4.png
common_captcha/resource/defaultImages/jigsaw/original/5.png
common_captcha/resource/defaultImages/jigsaw/slidingBlock/1.png
common_captcha/resource/defaultImages/jigsaw/slidingBlock/2.png
common_captcha/resource/defaultImages/jigsaw/slidingBlock/3.png
common_captcha/resource/defaultImages/jigsaw/slidingBlock/4.png
common_captcha/resource/defaultImages/jigsaw/slidingBlock/5.png
common_captcha/resource/defaultImages/jigsaw/slidingBlock/6.png
common_captcha/resource/defaultImages/pic-click/1.png
common_captcha/resource/defaultImages/pic-click/2.png
common_captcha/resource/defaultImages/pic-click/3.png
common_captcha/resource/defaultImages/pic-click/4.png
common_captcha/resource/defaultImages/pic-click/5.png
common_captcha/resource/defaultImages/pic-click/6.png
common_captcha/resource/defaultImages/pic-click/bg10.png
common_captcha/resource/defaultImages/pic-click/bg11.png
common_captcha/resource/defaultImages/pic-click/bg12.png
common_captcha/resource/defaultImages/pic-click/bg13.png
common_captcha/resource/defaultImages/pic-click/bg14.png
common_captcha/resource/defaultImages/pic-click/bg15.png
common_captcha/resource/defaultImages/pic-click/bg16.png
common_captcha/resource/defaultImages/pic-click/bg17.png
common_captcha/resource/defaultImages/pic-click/bg18.png
common_captcha/resource/defaultImages/pic-click/bg19.png
common_captcha/resource/defaultImages/pic-click/bg20.png
common_captcha/resource/fonts/WenQuanZhengHei.ttf
common_captcha-1.0.5.dist-info/LICENSE
common_captcha-1.0.5.dist-info/METADATA
common_captcha-1.0.5.dist-info/WHEEL
common_captcha-1.0.5.dist-info/top_level.txt
common_captcha-1.0.5.dist-info/RECORD
